<?xml version = '1.0' encoding = 'UTF-8'?>
<Relation class="oracle.dbtools.crest.model.design.logical.Relation" name="Election_Contest" directorySegmentName="seg_0" id="C2A58636-BE20-6E6D-BAAB-97C4256C4054">
<createdBy>john</createdBy>
<createdTime>2020-12-08 12:58:55 UTC</createdTime>
<ownerDesignName>cvr</ownerDesignName>
<engineerTo>
<item key="C507ADBB-6364-1BD9-DF9F-98A5D1B602E7" value="true"/>
</engineerTo>
<useSurrogateKey>true</useSurrogateKey>
<identifying>false</identifying>
<optionalSource>false</optionalSource>
<optionalTarget>false</optionalTarget>
<sourceCardinality>*</sourceCardinality>
<sourceEntity>0FA69530-4FAD-32D8-C644-71A331E6F06A</sourceEntity>
<targetCardinalityString>1</targetCardinalityString>
<targetEntity>C886BA6E-AE22-3DB7-7607-24DFC5066580</targetEntity>
<transferable>true</transferable>
<deleteRule>NO ACTION</deleteRule>
</Relation>